pyramid_ldap3/__init__.py
pyramid_ldap3-0.5.dist-info/LICENSE.txt
pyramid_ldap3-0.5.dist-info/METADATA
pyramid_ldap3-0.5.dist-info/WHEEL
pyramid_ldap3-0.5.dist-info/entry_points.txt
pyramid_ldap3-0.5.dist-info/top_level.txt
pyramid_ldap3-0.5.dist-info/RECORD
