Metadata-Version: 2.1
Name: pyramid-ldap3
Version: 0.5
Summary: pyramid_ldap3
Home-page: https://trypyramid.com/extending-pyramid.html
Author: Chris McDonough, Christoph Zwerschke
Author-email: pylons-discuss@googlegroups.com
License: BSD-derived (Repoze)
Keywords: web,pyramid,pylons,ldap,auth,authentication
Platform: UNKNOWN
Classifier: Framework :: Pyramid
Classifier: Programming Language :: Python
Classifier: Programming Language :: Python :: 2
Classifier: Programming Language :: Python :: 2.7
Classifier: Programming Language :: Python :: 3
Classifier: Programming Language :: Python :: 3.5
Classifier: Programming Language :: Python :: 3.6
Classifier: Programming Language :: Python :: 3.7
Classifier: Programming Language :: Python :: 3.8
Classifier: Programming Language :: Python :: 3.9
Classifier: Programming Language :: Python :: 3.10
Classifier: Topic :: Software Development :: Libraries :: Python Modules
Classifier: Topic :: System :: Systems Administration :: Authentication/Directory :: LDAP
Classifier: Intended Audience :: Developers
Classifier: Development Status :: 4 - Beta
Classifier: License :: Repoze Public License
License-File: LICENSE.txt
Requires-Dist: pyramid (>=1.4)
Requires-Dist: ldap3 (>=2.0)
Provides-Extra: docs
Requires-Dist: Sphinx (<4,>=3) ; extra == 'docs'
Requires-Dist: repoze.sphinx.autointerface (<1,>=0.8) ; extra == 'docs'
Requires-Dist: pylons-sphinx-themes (>=1.0.8) ; extra == 'docs'
Provides-Extra: sampleapp
Requires-Dist: waitress ; extra == 'sampleapp'
Requires-Dist: pyramid-chameleon ; extra == 'sampleapp'
Requires-Dist: pyramid-debugtoolbar ; extra == 'sampleapp'
Provides-Extra: testing
Requires-Dist: coverage ; extra == 'testing'
